xchg/__init__.py
xchg/main.py
gexchange-0.0.3.dist-info/LICENSE
gexchange-0.0.3.dist-info/METADATA
gexchange-0.0.3.dist-info/WHEEL
gexchange-0.0.3.dist-info/entry_points.txt
gexchange-0.0.3.dist-info/top_level.txt
gexchange-0.0.3.dist-info/RECORD
