Metadata-Version: 2.1
Name: gexchange
Version: 0.0.3
Summary: A simple Python CLI tool using which you can see exchange rates among different currencies of the world in your Terminal.
Home-page: https://github.com/iamtalhaasghar/gexchange
Author: Talha Asghar
Author-email: talhaasghar.contact@simplelogin.fr
License: UNKNOWN
Platform: UNKNOWN
Classifier: Programming Language :: Python :: 3
Classifier: License :: OSI Approved :: GNU General Public License v3 (GPLv3)
Classifier: Operating System :: OS Independent
Requires-Python: >=3.6
License-File: LICENSE
Requires-Dist: bs4
Requires-Dist: requests
